DS1631.py
DS1631-0.3.6.dist-info/LICENSE
DS1631-0.3.6.dist-info/METADATA
DS1631-0.3.6.dist-info/WHEEL
DS1631-0.3.6.dist-info/top_level.txt
DS1631-0.3.6.dist-info/RECORD
