Metadata-Version: 2.1
Name: DS1631
Version: 0.3.6
Summary: Raspberry pi i2c interface for Maxim-Dallas DS1621 DS1631 DS1631A DS1721 DS1731 digital thermometer and thermostat.
Home-page: UNKNOWN
Author: Fabrice Sincère
Author-email: fabrice.sincere@wanadoo.fr
License: GNU General Public License v3.0
Platform: UNKNOWN
Requires-Python: >=3
